doc_manager/__init__.py
doc_manager/admin.py
doc_manager/apps.py
doc_manager/locale/en/LC_MESSAGES/django.mo
doc_manager/locale/en/LC_MESSAGES/django.po
doc_manager/locale/pl/LC_MESSAGES/django.mo
doc_manager/locale/pl/LC_MESSAGES/django.po
doc_manager/models.py
doc_manager/templates/admin_change_form_documents.html
doc_manager/version.py
doc_manager/views.py
doc_manager-1.0.2.dist-info/LICENSE
doc_manager-1.0.2.dist-info/METADATA
doc_manager-1.0.2.dist-info/WHEEL
doc_manager-1.0.2.dist-info/RECORD
