Metadata-Version: 2.1
Name: doc-manager
Version: 1.0.2
Summary: doc_manager is a django library for publishing documents in pdf and html format like privacy policy or term of use.
License: MIT
Author: ImpiCode
Requires-Python: >=3.7,<4.0
Classifier: License :: OSI Approved :: MIT License
Classifier: Programming Language :: Python :: 3
Classifier: Programming Language :: Python :: 3.7
Classifier: Programming Language :: Python :: 3.8
Classifier: Programming Language :: Python :: 3.9
Classifier: Programming Language :: Python :: 3.10
Classifier: Programming Language :: Python :: 3.11
Requires-Dist: Django (>=3.2.17)
